cyhelllo/__init__.py
cyhelllo-0.1.0.dist-info/LICENSE
cyhelllo-0.1.0.dist-info/METADATA
cyhelllo-0.1.0.dist-info/WHEEL
cyhelllo-0.1.0.dist-info/top_level.txt
cyhelllo-0.1.0.dist-info/RECORD
